{
    "src_link": "https://news.google.com/topics/CAAqIggKIhxDQkFTRHdvSkwyMHZNRGw1Y3pjd0VnSndiQ2dBUAE?hl=pl&gl=PL&ceid=PL:pl",
    "language": "pl",
    "get_time": "2018-12-08 11:18:27 GMT",
    "content": [
        {
            "title": "\u65b0\u515a\u306e\u821e\u53f0\u88cf\u3002 \u300c\u30c7\u30a3\u30ec\u30af\u30bf\u30fc\u306e\u7236\u89aa\u306f\u3001PiS\u304c\u3072\u3069\u3044\u3068\u601d\u3063\u3066\u3044\u307e\u3059\u3002\u300d - \u30d0\u30fc\u30c1\u30e3\u30eb\u30dd\u30fc\u30e9\u30f3\u30c9",
            "link": "https://wiadomosci.wp.pl/kulisy-powstania-nowej-partii-ojciec-dyrektor-uwaza-ze-pis-jest-skapy-6325291311679617a",
            "pub_date": "2018-12-08 09:23:59 GMT",
            "source_nm": "\u30d0\u30fc\u30c1\u30e3\u30eb\u30dd\u30fc\u30e9\u30f3\u30c9",
            "source_url": "https://wiadomosci.wp.pl",
            "desc": ""
        },
        {
            "title": "Rydzyk\u7236\u306f\u3069\u3053\u304b\u3089\u6765\u305f\u306e\u3067\u3059\u304b\uff1fGazeta Wyborcza",
            "link": "http://wyborcza.pl/magazyn/7,124059,24253676,skad-sie-wzial-ojciec-rydzyk.html",
            "pub_date": "2018-12-08 05:00:21 GMT",
            "source_nm": "\u30ac\u30bc\u30bf\u30fb\u30ef\u30a4\u30dc\u30e9",
            "source_url": "http://wyborcza.pl",
            "desc": "Wszyscy m\u00f3wi\u0105: a, Tadeusz robi parti\u0119, czyli pr\u00f3buje postawi\u0107 Kaczy\u0144skiego pod \u015bcian\u0105. Prawda, ale nie ca\u0142a. Jak nie wiadomo, o co chodzi, chodzi o ..."
        },
        {
            "title": "Stanis\u0142awGaw\u0142owski\u306f\u5f7c\u306e\u554f\u984c\u306e\u300c\u6709\u7f6a\u300d\u3092\u767a\u898b\u3057\u305f\u3002\u5f7c\u306fTadeusz Rydzyk  -  Wirtualna Polska\u3092\u6307\u6458\u3057\u305f",
            "link": "https://wiadomosci.wp.pl/stanislaw-gawlowski-znalazl-winnego-swoich-problemow-wskazal-na-tadeusza-rydzyka-6323920926222465a",
            "pub_date": "2018-12-04 12:54:00 GMT",
            "source_nm": "\u30d0\u30fc\u30c1\u30e3\u30eb\u30dd\u30fc\u30e9\u30f3\u30c9",
            "source_url": "https://wiadomosci.wp.pl",
            "desc": "Kiedy\u015b zdarzy\u0142o mi si\u0119 cofn\u0105\u0107 mu Tadeuszowi Rydzykowi dotacj\u0119 na Geotermi\u0119 w Toruniu i wtedy us\u0142ysza\u0142em od jednego z wa\u017cnych dzisiaj kardyna\u0142\u00f3w, ..."
        },
        {
            "title": "\u6559\u6388Jadwiga Staniszkis\uff1aPyd\u3068\u306e\u6226\u3044\u306b\u304a\u3051\u308b\u6559\u4f1a\u306e\u9053\u5177\u3068\u3057\u3066\u306eRydzyk  -  SuperBiz.SE.pl",
            "link": "https://www.se.pl/wiadomosci/polityka/prof-jadwiga-staniszkis-rydzyk-narzedziem-kosciola-w-walce-z-pis-aa-ZPhh-SQMy-cy8U.html",
            "pub_date": "2018-12-08 04:00:35 GMT",
            "source_nm": "SuperBiz.SE.pl",
            "source_url": "https://www.se.pl",
            "desc": "Rydzyk jest du\u017co bardziej skomplikowan\u0105 postaci\u0105 ni\u017c stereotypy, kt\u00f3re kr\u0105\u017c\u0105 na jego temat. My\u015bl\u0119, \u017ce si\u0119 z Ko\u015bcio\u0142em pr\u00f3buje pogodzi\u0107, a jego powr\u00f3t do ..."
        },
        {
            "title": "Rydzyk\u306fPiS\u306b\u5bfe\u3059\u308b\u5f7c\u306e\u611b\u3092\u6570\u3048\u3066\u3044\u307e\u3059\u304b\uff1f\u6cd5\u6848\u306f21\u5e74\u9593\u767a\u884c\u3055\u308c\u3066\u3044\u307e\u3059 -  Gazeta.pl\u306e\u30cb\u30e5\u30fc\u30b9",
            "link": "http://wiadomosci.gazeta.pl/wiadomosci/7,114884,24243590,ile-o-rydzyk-policzy-sobie-za-swa-milosc-do-pis-rachunki-wystawia.html",
            "pub_date": "2018-12-05 10:39:00 GMT",
            "source_nm": "Gazeta.pl\u306e\u30cb\u30e5\u30fc\u30b9",
            "source_url": "http://wiadomosci.gazeta.pl",
            "desc": "Po raz pierwszy Jaros\u0142aw Kaczy\u0144ski z o. Tadeuszem Rydzykiem spotkali si\u0119 w 1997 r. Rozmawiali p\u00f3\u0142 nocy. Nic si\u0119 nie klei\u0142o. Kaczy\u0144ski najpierw utyskiwa\u0142 na ..."
        },
        {
            "title": "Rydzyk\u306e\u7236\u89aa\u306e\u4fe1\u983c\u3067\u304d\u308b\u4eba\u304c\u30d1\u30fc\u30c6\u30a3\u30fc\u3092\u3059\u308b\u3002\u79c1\u305f\u3061\u306f\u88c1\u5224\u6240\u304b\u3089\u306e\u60c5\u5831\u3092\u6301\u3063\u3066\u3044\u307e\u3059 -  Wirtualna Polska",
            "link": "https://wiadomosci.wp.pl/zaufany-czlowiek-ojca-rydzyka-zaklada-partie-mamy-informacje-z-sadu-6324270964123777a",
            "pub_date": "2018-12-05 12:30:00 GMT",
            "source_nm": "\u30d0\u30fc\u30c1\u30e3\u30eb\u30dd\u30fc\u30e9\u30f3\u30c9",
            "source_url": "https://wiadomosci.wp.pl",
            "desc": ""
        },
        {
            "title": "Piotrowicz\u306fRydzyk\u7236\u89aa\u3067\u8e0a\u3063\u3066\u3044\u307e\u3059\uff01\u507d\u5584\uff1f -  fakt.pl",
            "link": "https://www.fakt.pl/wydarzenia/polityka/czlonkowie-rzadu-tancza-na-urodzinach-radia-maryja-abba-ojcze/8hgb2t4",
            "pub_date": "2018-12-02 19:56:02 GMT",
            "source_nm": "fakt.pl",
            "source_url": "https://www.fakt.pl",
            "desc": "Ka\u017cdy ma prawo do szczerego i nieszczerego manifestowania wiary. Ka\u017cdy ma prawo do uczestnictwa w uroczysto\u015bciach religijnych z kim chce i gdzie chce."
        },
        {
            "title": "\u5f7c\u306e\u90fd\u5e02\u306e\u9632\u885b\u306eMyrch\u306e\u4ee3\u7406\u4eba\uff1aRydzyk\u306fToru\u0144\u3067\u306f\u3042\u308a\u307e\u305b\u3093\uff01 -  onTemat",
            "link": "https://natemat.pl/257041,posel-myrcha-wystapil-z-apelem-by-nie-utozsamiac-rydzyka-z-toruniem",
            "pub_date": "2018-12-05 20:07:20 GMT",
            "source_nm": "naTemat",
            "source_url": "https://natemat.pl",
            "desc": "Rodzinnym miastem pos\u0142a PO Arkadiusza Myrchy jest Toru\u0144, dlatego nie dziwi jego apel, by przesta\u0107 uto\u017csamia\u0107 je tylko z Tadeuszem Rydzykiem. \"Rydzyk to ..."
        },
        {
            "title": "Rydzyk\u7236\u89aa\u306e\u30b0\u30eb\u30fc\u30d7\u5206\u3051\uff1f Adam Bielan\u306fOnet In the Morning  -  Straight\u306b\u3064\u3044\u3066\u30b3\u30e1\u30f3\u30c8\u3057\u3066\u3044\u307e\u3059",
            "link": "https://www.wprost.pl/polityka/10173567/adam-bielan-nie-wierzy-w-ugrupowanie-o-rydzyka-to-jest-plotka-ploteczka.html",
            "pub_date": "2018-12-05 09:08:00 GMT",
            "source_nm": "\u76f4\u306b",
            "source_url": "https://www.wprost.pl",
            "desc": ""
        },
        {
            "title": "Rydzyk\u306f\u30e2\u30c7\u30ec\u30fc\u30b7\u30e7\u30f3\u3092\u77e5\u3089\u306a\u3044\uff01\u3059\u3079\u3066\u3092\u5909\u3048\u308b\u3082\u306e\u3092\u767a\u8868 -  Pikio.pl  - \u516c\u5e73\u306a\u60c5\u5831\u30dd\u30fc\u30bf\u30eb",
            "link": "https://pikio.pl/tadeusz-rydzyk-nie-zna-umiaru/",
            "pub_date": "2018-12-06 09:35:51 GMT",
            "source_nm": "Pikio.pl  - \u516c\u5e73\u306a\u60c5\u5831\u30dd\u30fc\u30bf\u30eb",
            "source_url": "https://pikio.pl",
            "desc": ""
        },
        {
            "title": "Barbara Nowacka\uff1aPiS\u306f\u3001Rydzyk\u6c0f\u306e\u3088\u3046\u306a\u304a\u91d1\u3092\u7d04\u675f\u3057\u305f\u305f\u3081\u306b\u7372\u5f97\u3057\u307e\u3057\u305f\u3002 -  Rzeczpospolita",
            "link": "https://www.rp.pl/Prawo-i-Sprawiedliwosc/181209909-Barbara-Nowacka-PiS-wygralo-bo-obiecalo-pieniadze-takim-jak-o-Rydzyk.html",
            "pub_date": "2018-12-03 08:15:00 GMT",
            "source_nm": "\u5171\u548c\u56fd",
            "source_url": "https://www.rp.pl",
            "desc": "Mam pe\u0142ny szacunek dla ludzi wiary, ale czy instytucje pa\u0144stwa koniecznie musz\u0105 istnie\u0107 pod dyktando ko\u015bcio\u0142a? - pyta Barbara Nowacka."
        },
        {
            "title": "Grzegorz Kramer\u7236\u306f &quot;Kler&quot;\u306b\u3064\u3044\u3066Rydzek\u7236\u89aa\u306b\u7b54\u3048\u307e\u3057\u305f\u3002 \u300c\u79c1\u306f\u79c1\u306e\u76e3\u7763\u3067\u3042\u308a\u3001\u304b\u3064\u3066\u3042\u3063\u305f\u300d -  Wirtualna Polska",
            "link": "https://wiadomosci.wp.pl/o-grzegorz-kramer-odpowiedzial-o-rydzykowi-ws-kleru-ja-bylem-i-byl-moj-biskup-6323214962230913a",
            "pub_date": "2018-12-02 12:39:00 GMT",
            "source_nm": "\u30d0\u30fc\u30c1\u30e3\u30eb\u30dd\u30fc\u30e9\u30f3\u30c9",
            "source_url": "https://wiadomosci.wp.pl",
            "desc": "O. Tadeusz Rydzyk \u015bwi\u0119towa\u0142 w sobot\u0119 27. urodziny Radia Maryja. Podczas jego przem\u00f3wienia nie zabrak\u0142o gorzkich refleksji na temat popularno\u015bci filmu ..."
        },
        {
            "title": "Rydzyk\u7236\u306e\u30d1\u30fc\u30c6\u30a3\u30fc\u3067\u4e0a\u9662\u8b70\u54e1S. Karczewski\u306e\u8b1b\u6f14\u8005\u3001\u30ce\u30ed\u30c1\u30a7\u30b9\u30ca\u306e\u4e2d\u7d76\u3068\u5371\u6a5f - \u30e9\u30b8\u30aaZET",
            "link": "https://wiadomosci.radiozet.pl/Polska/Marszalek-Senatu-S.-Karczewski-o-partii-o.-Rydzyka-aborcji-i-kryzysie-w-Nowoczesnej",
            "pub_date": "2018-12-06 09:00:00 GMT",
            "source_nm": "ZET\u30e9\u30b8\u30aa",
            "source_url": "https://wiadomosci.radiozet.pl",
            "desc": "To koniec Nowoczesnej. Grzegorz Schetyna ich po\u017car\u0142 - m\u00f3wi Stanis\u0142aw Karczewski. Karczewski komentuje te\u017c doniesienia dot. nowej partii pod egid\u0105 ..."
        },
        {
            "title": "\u79c1\u305f\u3061\u306e\u30a4\u30f3\u30bf\u30d3\u30e5\u30fc\u3002 JanMosi\u0144ski\uff1a\u7236Tadeusz Rydzyk\u306b\u3064\u3044\u3066\u306e\u30bf\u30a4\u30c8\u30eb\u306f\u30d1\u30fc\u30c6\u30a3\u30fc\u304c\u73fe\u5b9f\u3068\u306f\u95a2\u4fc2\u306a\u3044\u3068\u4eee\u5b9a\u3057\u3066\u3044\u307e\u3059 -  wPolityce.pl",
            "link": "https://wpolityce.pl/polityka/424227-mosinski-o-rydzyk-nie-zaklada-partii",
            "pub_date": "2018-12-05 13:52:00 GMT",
            "source_nm": "wPolityce.pl",
            "source_url": "https://wpolityce.pl",
            "desc": "\"Eurodeputowany Piotrowski rejestruje parti\u0119, ale nie spowoduje to \u017cadnych nerwowych reakcji w naszym obozie\"."
        },
        {
            "title": "Rydzyk\u306e\u7236\u89aa\u306f\u3001\u30dd\u30fc\u30e9\u30f3\u30c9\u6620\u753b\u7814\u7a76\u6240\u306b\u3054\u3081\u3093\u306a\u3055\u3044\u3002\u305d\u308c\u306f\u304a\u91d1\u3068\u6620\u753b &quot;Kler&quot;\u306e\u305f\u3081\u306b\u884c\u304d\u307e\u3057\u305f -  Wirtualna Polska",
            "link": "https://wiadomosci.wp.pl/ojciec-rydzyk-ma-zal-do-pisf-poszlo-o-pieniadze-i-film-kler-6322944133092993a",
            "pub_date": "2018-12-01 18:12:00 GMT",
            "source_nm": "\u30d0\u30fc\u30c1\u30e3\u30eb\u30dd\u30fc\u30e9\u30f3\u30c9",
            "source_url": "https://wiadomosci.wp.pl",
            "desc": "Kto z was by\u0142, r\u0119ka do g\u00f3ry, na filmie \"Kler\"? Przyznajcie si\u0119, jak \u017ce\u015bcie do\u0142o\u017cyli pieni\u0105dze do tamtej kasy, \u017ceby dalej szkodzili - pyta\u0142 Tadeusz Rydzyk na 27."
        },
        {
            "title": "&quot;\u30d0\u30b7\u30af\u306f\u30ab\u30c1\u30e3\u30f3\u30b9\u30ad\u30fc\u306b\u3072\u3069\u3044\u3067\u3059&quot; Rydzyk\u306e\u515a\u306eAr\u0142ukowicz -  polsatnews.pl",
            "link": "http://www.polsatnews.pl/wiadomosc/2018-12-05/wydarzenia-i-opinie-arlukowicz-cymanski-scheuring-wielgus-terlikowski/",
            "pub_date": "2018-12-05 18:48:00 GMT",
            "source_nm": "polsatnews.pl",
            "source_url": "http://www.polsatnews.pl",
            "desc": "Nied\u0142ugo b\u0119d\u0105 przydzielane miejsca do europarlamentu. O. Rydzyk lubi mie\u0107 swoj\u0105 dru\u017cyn\u0119 w ka\u017cdej ekipie. Jest to pewnego rodzaju forma presji. Jak nie ..."
        },
        {
            "title": "\u8ca7\u3057\u3044\u6620\u753b\u306f270\u4e07\u306ePLN\u3092\u88dc\u52a9\u91d1\u3067\u53d7\u3051\u53d6\u3063\u3066\u3044\u307e\u305b\u3093\u3067\u3057\u305f\u3002\u79c1\u305f\u3061\u306f\u3001Tadeusz Rydzyk  -  Wirtualna Polska\u7236\u306e\u4e0d\u6e80\u306b\u3064\u3044\u3066\u8aac\u660e\u3057\u307e\u3059\u3002",
            "link": "https://wiadomosci.wp.pl/na-kiepski-film-nie-dostal-27-mln-zl-dotacji-wyjasniamy-zale-o-tadeusza-rydzyka-6323905702844033a",
            "pub_date": "2018-12-04 11:31:00 GMT",
            "source_nm": "\u30d0\u30fc\u30c1\u30e3\u30eb\u30dd\u30fc\u30e9\u30f3\u30c9",
            "source_url": "https://wiadomosci.wp.pl",
            "desc": "Wyja\u015bni\u0142o si\u0119 dlaczego o. Tadeusz Rydzyk tak ostro skrytykowa\u0142 dotacj\u0119 dla filmu \"Kler\" oraz dzia\u0142alno\u015b\u0107 Polskiego Instytutu Sztuki Filmowej. Jego film \"N\u0119dzarz ..."
        },
        {
            "title": "Jankowski\u7236 - \u8ab0\u3082\u304c\u77e5\u3063\u3066\u3044\u305f - \u30b9\u30c8\u30ec\u30fc\u30c8",
            "link": "https://www.wprost.pl/tylko-u-nas/10174257/ksiadz-jankowski-wszyscy-wiedzieli.html",
            "pub_date": "2018-12-07 17:32:00 GMT",
            "source_nm": "\u76f4\u306b",
            "source_url": "https://www.wprost.pl",
            "desc": "\u017by\u0142 jak gwiazda, jak bogacz, to wystarczy\u0142o, \u017ceby reagowa\u0107, nie trzeba by\u0142o czeka\u0107 na twarde dowody pedofilii. Jednak Henryk Jankowski przez ca\u0142e \u017cycie pozostawa\u0142 jawnie bezkarny. Wszyscy wiedzieli \u2013 to pierwsza my\u015bl pojawiaj\u0105ca si\u0119 podczas czytania wstrz\u0105saj\u0105cego reporta\u017cu Bo\u017ceny Aksamit z Du\u017cego Formatu o ksi\u0119dzu Henryku Jankowskim, kapelanie Solidarno\u015bci, kt\u00f3ry, jak czytamy w tek\u015bcie, gwa\u0142ci\u0142 dzieci.To pytanie jest jednak bardziej skomplikowane \u2013 kto wiedzia\u0142 i o czym. Najwa\u017cniejsze \u2013 o czym wiedzia\u0142 biskup Edmund Nowicki, kt\u00f3ry przenosi\u0142 ksi\u0119dza z parafii do parafii. Czy robi\u0142 to, bo wi..."
        },
        {
            "title": "Rydzyk\u7236\u306f\u5f7c\u306e\u5e1d\u56fd\u3092\u62e1\u5927\u3059\u308b\u4e88\u5b9a\u3067\u3059\u3002\u3068\u308a\u308f\u3051\u65b0\u3057\u3044\u65b0\u805e\u3068\u516c\u5712\u306e\u305f\u3081\u306b - \u516c\u5712 -  Dziennik.pl",
            "link": "https://wiadomosci.dziennik.pl/polityka/artykuly/586722,o-rydzyk-nowa-gazeta-park-pamieci-dotacje-pis.html",
            "pub_date": "2018-12-06 10:59:00 GMT",
            "source_nm": "Dziennik.pl",
            "source_url": "https://wiadomosci.dziennik.pl",
            "desc": "Grupa medialna, kt\u00f3rej patronuje o. Tadeusz Rydzyk, sk\u0142ada si\u0119 z Radia Maryja, jego internetowego odpowiednika, Tv Trwam, gazety \"Nasz Dziennik\", miesi\u0119cznika \"W Naszej Rodzinie\" i - uruchomionego przy znacznym wsparciu ministerstwa sprawiedliwo\u015bci - portalu Ostrzegamy.online. \"Ta grupa medialna nie powinna narzeka\u0107 na brak rz\u0105dowego wsparcia w r\u00f3\u017cnych formach. Mimo to redemptory\u015bci na tym nie poprzestan\u0105\" - opisuje Onet. I cytuje s\u0142owa o. Rydzyka: \"Nied\u0142ugo b\u0119dzie nast\u0119pny miesi\u0119cznik, nast\u0119pny tytu\u0142\". Duchowny nie zaniedbuje starszych inwestycji, przede wszystkim Wy\u017cszej Szko\u0142y Kultury Sp..."
        },
        {
            "title": "\u8ab0\u304c\u65b0\u3057\u3044\u30d1\u30fc\u30c6\u30a3\u30fc\u306e\u5f8c\u308d\u306b\u3044\u308b\u306e\uff1f\u30de\u30fc\u30b7\u30e3\u30eb\uff1a\u305d\u308c\u306fRydzyk\u3067\u306f\u306a\u3044 - \u3082\u306e\u3092\u3059\u308b",
            "link": "https://www.dorzeczy.pl/obserwator-mediow/86038/kto-stoi-za-nowa-partia-na-prawicy-marszalek-to-nie-rydzyk.html",
            "pub_date": "2018-12-06 09:18:00 GMT",
            "source_nm": "\u7269\u4e8b\u3078",
            "source_url": "https://www.dorzeczy.pl",
            "desc": "Marsza\u0142ek Senatu Stanis\u0142aw Karczewski o\u015bwiadczy\u0142, \u017ce za Ruchem Prawdziwa Europa nie stoi dyrektor Radia Maryja o. Tadeusz Rydzyk, lecz europose\u0142 Miros\u0142aw Piotrowski, kt\u00f3rego nazwa\u0142 \"nielojalnym politykiem\". We wtorek Wirtualna Polska poda\u0142a, \u017ce do S\u0105du Okr\u0119gowego w Warszawie wp\u0142yn\u0105\u0142 wniosek o rejestracj\u0119 nowej partii politycznej \u2013 Ruch Prawdziwa Europa. Dokumenty mia\u0142 z\u0142o\u017cy\u0107 zaufany cz\u0142owiek ojca Rydzyka, europose\u0142 Miros\u0142aw Piotrowski. O sprawie m\u00f3wi\u0142 w Radiu Zet Stanis\u0142aw Karczewski z PiS. \u2013 Znam bardzo dobrze ojca dyrektora, bardzo cz\u0119sto z nim rozmawiam, to jest wspania\u0142y cz\u0142owiek i wiem..."
        },
        {
            "title": "\u6559\u6388Kik\uff1a\u5f7c\u306e\u515a\u3092\u4f5c\u308b\u3053\u3068\u3067\u3001Rydzyk\u7236\u306fPiS\u3092\u5185\u90e8\u304b\u3089\u53d6\u308a\u305f\u3044\u3068\u601d\u3063\u3066\u3044\u307e\u3059 -  Dziennik.pl",
            "link": "https://wiadomosci.dziennik.pl/opinie/artykuly/586633,o-rydzyk-partia-ruch-prawdziwej-europy-pis-prawica-kik.html",
            "pub_date": "2018-12-05 09:06:00 GMT",
            "source_nm": "Dziennik.pl",
            "source_url": "https://wiadomosci.dziennik.pl",
            "desc": "Czy partia o. Tadeusza Rydzyka ma szans\u0119 zaistnie\u0107 w polityce? Prof. Kik: Pytanie brzmi raczej: czy ma jakikolwiek sens dla obozu Zjednoczonej Prawicy? A ma? Bardzo w\u0105tpliwy. Metoda D\u2019Hondta, stosowana w Polsce do podzia\u0142u mandat\u00f3w w wyborach, preferuje du\u017ce polityczne byty. Czyli jedno\u015b\u0107 w partyjnych szeregach. Natomiast to, co robi ob\u00f3z toru\u0144ski jest pr\u00f3b\u0105 stworzenia instrumentu wp\u0142ywu w prawicowym obozie. Do\u0142o\u017cenie czwartego elementu do obecnego PiS, z przybud\u00f3wkami Jaros\u0142awa Gowina i Zbigniewa Ziobry, os\u0142abi ten tw\u00f3r. Prawica straci mo\u017cliwo\u015b\u0107 scentralizowanego dzia\u0142ania. Dziwne, \u017ce o. R..."
        },
        {
            "title": "&quot;Rydzyk party&quot;\u306f\u3069\u3046\u3067\u3059\u304b\uff1f Macierewicz\u306e\u660e\u308b\u3044\u30dd\u30b8\u30b7\u30e7\u30f3 -  To Things",
            "link": "https://www.dorzeczy.pl/obserwator-mediow/85905/co-z-partia-rydzyka-jasne-stanowisko-macierewicza.html",
            "pub_date": "2018-12-05 06:05:00 GMT",
            "source_nm": "\u7269\u4e8b\u3078",
            "source_url": "https://www.dorzeczy.pl",
            "desc": "By\u0142y szef MON Antoni Macierewicz powiedzia\u0142 w TV Republika, \u017ce w sprawie tzw. partii ojca Tadeusza Rydzyka mo\u017cemy mie\u0107 do czynienia z fake newsem. We wtorek Wirtualna Polska poda\u0142a, \u017ce do S\u0105du Okr\u0119gowego w Warszawie wp\u0142yn\u0105\u0142 wniosek o rejestracj\u0119 nowej partii politycznej \u2013 Ruch Prawdziwa Europa. Dokumenty mia\u0142 z\u0142o\u017cy\u0107 zaufany cz\u0142owiek ojca Rydzyka, europose\u0142 Miros\u0142aw Piotrowski. Doniesienia WP komentowa\u0142 na antenie Telewizji Republika Antoni Macierewicz. By\u0142y minister obrony powiedzia\u0142, \u017ce \"mamy do czynienia z pr\u00f3b\u0105 stworzenia faktu medialnego\". Jak doda\u0142, z dyrektorem Radia Maryja rozmawia\u0142 ..."
        },
        {
            "title": "\u4fe1\u3058\u3089\u308c\u305f\u7537\u3001Rydzyk\u7236\u306f\u3001\u30d1\u30fc\u30c6\u30a3\u30fc\u3092\u5f15\u304d\u7d99\u3050\u3002\u5f7c\u306f\u3059\u3067\u306b\u6cd5\u5ef7\u3067\u66f8\u985e\u3092\u63d0\u51fa\u3057\u3066\u3044\u307e\u3059 -  Dziennik.pl",
            "link": "https://wiadomosci.dziennik.pl/polityka/artykuly/586599,partia-o-rydzyk-ruch-prawdziwa-europa-zarejestrowana.html",
            "pub_date": "2018-12-04 17:34:00 GMT",
            "source_nm": "Dziennik.pl",
            "source_url": "https://wiadomosci.dziennik.pl",
            "desc": "Wniosek o zarejestrowanie partii zosta\u0142 z\u0142o\u017cony w ubieg\u0142ym tygodniu. Pe\u0142nomocnikiem \"Ruchu Prawdziwa Europa\" jest europose\u0142 Miros\u0142aw Piotrowski, kt\u00f3ry cho\u0107 nigdy nie by\u0142 cz\u0142onkiem PiS, w wyborach startowa\u0142 z list tej partii. O tym, \u017ce powstanie nowej partii jest wy\u0142\u0105cznie kwesti\u0105 czasu \u015bwiadczy\u0142y, zdaniem Wirtualnej Polski, kolej wydarzenia. Cho\u0107by brak poparcia o. Rydzyka dla PiS w wyborach samorz\u0105dowych. Co, z kolei, mia\u0142o by\u0107 konsekwencj\u0105 usuni\u0119cia z rz\u0105du kolejnych ministr\u00f3w: Jana Szyszki, Witolda Waszczykowskiego i Krzysztofa Jurgiela. \"O. Tadeusz Rydzyk ma te\u017c ubolewa\u0107 nad zbyt ma\u0142ym ..."
        },
        {
            "title": "\u300c\u30ea\u30b8\u30e7\u30af\u306f\u79c1\u306b\u5fa9\u8b90\u3057\u307e\u3059\u3002\u300d Gaw\u0142owski\u306e\u9a5a\u304f\u3079\u304d\u7406\u8ad6 -  To Things",
            "link": "https://dorzeczy.pl/obserwator-mediow/85846/Rydzyk-sie-na-mnie-zemsci-Zaskakujaca-teoria-Gawlowskiego.html",
            "pub_date": "2018-12-04 10:50:00 GMT",
            "source_nm": "\u7269\u4e8b\u3078",
            "source_url": "https://dorzeczy.pl",
            "desc": "Stanis\u0142aw Gaw\u0142owski z Platformy Obywatelskiej uwa\u017ca, \u017ce jego problemy z prawem maj\u0105 zwi\u0105zek z o. Tadeuszem Rydzykiem, dyrektorem Radia Maryja. Przypomnijmy, \u017ce Stanis\u0142aw Gaw\u0142owski us\u0142ysza\u0142 zarzuty korupcyjne w zwi\u0105zku z tzw. afer\u0105 melioracyjn\u0105. W po\u0142owie lipca wyszed\u0142 z aresztu za por\u0119czeniem maj\u0105tkowym w wysoko\u015bci 500 tys. z\u0142. Kaucj\u0119 wp\u0142aci\u0142a rodzina polityka. \u2013 Par\u0119 dni temu by\u0142a rocznica funkcjonowania Radia Maryja. A ja mam pewien zwi\u0105zek z ojcem Rydzykiem, kt\u00f3ry powoduje, \u017ce ojciec Rydzyk i ca\u0142e to \u015brodowisko bardzo mnie nie lubi \u2013 przekonywa\u0142 na antenie RMF FM pose\u0142 Platformy. Dalej m..."
        },
        {
            "title": "Radio Maryja\u306e\u8a95\u751f\u65e5\u3002\u30e9\u30ea\u30c3\u30af\u30dd\u30fc\u30e9\u30f3\u30c9 -  Wprost\u306e\u6297\u8b70\u306f\u30c8\u30eb\u30f3\u3067\u884c\u308f\u308c\u305f",
            "link": "https://www.wprost.pl/kraj/10172711/urodziny-radia-maryja-w-toruniu-odbyl-sie-protest-polski-laickiej.html",
            "pub_date": "2018-12-02 07:53:00 GMT",
            "source_nm": "\u76f4\u306b",
            "source_url": "https://www.wprost.pl",
            "desc": "W sobot\u0119 odby\u0142y si\u0119 uroczysto\u015bci zwi\u0105zane z 27-leciem powstania Radia Maryja. Sympatycy rozg\u0142o\u015bni zgromadzili si\u0119 w Toruniu, gdzie obecni byli tak\u017ce czo\u0142owi politycy PiS. R\u00f3wnolegle w mie\u015bcie odbywa\u0142 si\u0119 protest przeciwko \u201ezale\u017cno\u015bci w\u0142adzy od ojca Tadeusza Rydzyka\u201d. Obchody 27. rocznicy powstania Radia Maryja odby\u0142y si\u0119 w sobot\u0119 w Toruniu. To tam w hali widowiskowo-sportowej zgromadzili si\u0119 dziennikarze, s\u0142uchacze oraz politycy. W planie obok wsp\u00f3lnego r\u00f3\u017ca\u0144ca i mszy \u015bwi\u0119tej by\u0142 tak\u017ce wyst\u0119p Zespo\u0142u Pie\u015bni i Ta\u0144ca Mazowsze. Na uroczysto\u015bciach pojawili si\u0119 m.in. Mateusz Morawiecki, Joachim ..."
        },
        {
            "title": "PiS\u653f\u6cbb\u5bb6\uff1aKaczy\u0144ski\u3068Rydzyk  -  Rezeczy\u306e\u9593\u306e\u6df1\u523b\u306a\u8ad6\u4e89",
            "link": "https://dorzeczy.pl/kraj/85726/Polityk-PiS-Powazny-spor-Kaczynskiego-z-o-Rydzykiem.html",
            "pub_date": "2018-12-03 06:35:00 GMT",
            "source_nm": "\u7269\u4e8b\u3078",
            "source_url": "https://dorzeczy.pl",
            "desc": "Absencja Jaros\u0142awa Kaczy\u0144skiego na 27-urodzinach Radia Maryja by\u0142a spowodowana narastaj\u0105cym konfliktem mi\u0119dzy prezesem PiS a o. Tadeuszem Rydzykiem \u2013 zapewnia polityk partii rz\u0105dz\u0105cej w rozmowie z \"Super Expressem\". Polityk Prawa i Sprawiedliwo\u015bci, kt\u00f3ry wola\u0142 pozosta\u0107 anonimowy, odni\u00f3s\u0142 si\u0119 do nieobecno\u015bci Kaczy\u0144skiego na sobotniej imprezie Radia Maryja. \"To nie przypadek, tylko efekt powa\u017cnego sporu prezesa PiS z ojcem Tadeuszem Rydzykiem\" \u2013 przekonuje w rozmowie z gazet\u0105. Polityk dodaje, \u017ce w roku 2016 i 2017 Kaczy\u0144ski r\u00f3wnie\u017c nie by\u0142 obecny na jubileuszu, ale zawsze pami\u0119ta\u0142, aby przys\u0142..."
        },
        {
            "title": "Rydzyk\u7236\u306f &quot;Kler&quot;\u306e\u304a\u91d1\u306b\u3064\u3044\u3066\u8a71\u3057\u307e\u3057\u305f\u3002 &quot;\u5f7c\u3089\u306f\u3069\u308c\u304f\u3089\u3044\u79c1\u305f\u3061\u306b\u4e0e\u3048\u305f\u306e\u3067\u3059\u304b\uff1f&quot; - \u7269\u4e8b\u3078",
            "link": "https://dorzeczy.pl/obserwator-mediow/85654/Ojciec-Rydzyk-mowil-o-pieniadzach-na-Kler-Ile-nam-dali.html",
            "pub_date": "2018-12-01 18:59:00 GMT",
            "source_nm": "\u7269\u4e8b\u3078",
            "source_url": "https://dorzeczy.pl",
            "desc": "Za\u0142o\u017cycieli Radia Maryja skrytykowa\u0142 Polski Instytut Sztuki Filmowej za dofinansowanie filmu \"Kler\" w re\u017cyserii Wojciecha Smarzowskiego. W sobot\u0119 odbywaj\u0105 si\u0119 uroczysto\u015bci zwi\u0105zane z 27. rocznic\u0105 powstania toru\u0144skiej rozg\u0142o\u015bni. O. Tadeusz Rydzyk nawi\u0105za\u0142 w swoim wyst\u0105pieniu do filmu \"Kler\". Redemptorysta ma \u017cal, \u017ce dofinansowa\u0142 go PISF. \u2013 Teraz robimy film \"N\u0119dzarz i madame\". Ten n\u0119dzarz to brat Albert, madame - Modrzejewska. W tym s\u0142owie madame ukryty jest Adam \u2013 m\u00f3wi ojciec Rydzyk o powstaj\u0105cym filmie po\u015bwi\u0119conym \u015bw. Albertowi Chmielowskiemu. \u2013 I wiecie co? Zwr\u00f3cili\u015bmy si\u0119 do takiej organ..."
        }
    ]
}