{
    "src_link": "https://news.google.com/topics/CAAqIQgKIhtDQkFTRGdvSUwyMHZNRGsyWjIwU0FuSnZLQUFQAQ?hl=ro&gl=RO&ceid=RO:ro",
    "language": "ro",
    "get_time": "2018-12-08 13:08:48 GMT",
    "content": [
        {
            "title": "Still a defeat for Gabriela Firea in court: Bucharest Court decided to suspend the decision on the abolition of the administrations subordinated to the City Hall - G4Media.ro",
            "link": "https://www.g4media.ro/inca-o-infrangere-pentru-gabriela-firea-in-instanta-tribunalul-bucuresti-a-decis-suspendarea-hotararii-privind-desfiintarea-administratiilor-din-subordinea-primariei-generale.html",
            "pub_date": "2018-12-08 09:18:39 GMT",
            "source_nm": "G4Media.ro",
            "source_url": "https://www.g4media.ro",
            "desc": "Pre\u015fedintele USR Bucure\u015fti, Roxana Wring, anun\u0163\u0103 c\u0103 Tribunalul Bucure\u015fti a decis vineri suspendarea execut\u0103rii Hot\u0103r\u00e2rii de Consiliu General al Capitalei."
        },
        {
            "title": "Gherghel plotting Oana Marinache - Adev\u0103rul",
            "link": "https://adevarul.ro/news/bucuresti/parcelarea-gherghel-1_5c0b5d56df52022f753cd081/index.html",
            "pub_date": "2018-12-08 06:17:04 GMT",
            "source_nm": "truth",
            "source_url": "https://adevarul.ro",
            "desc": "A.N.D.M.B., fond P.M.B. Tehnic, A.N.D.M.B., fond P.M.B. Tehnic, Spre nord mosia familiei Filipescu se invecina cu proprietatea colonelului Gherghel, azi strada ..."
        },
        {
            "title": "Strong fire at a house in Bucurestii Noi (Photo) - Ziare.com",
            "link": "http://www.ziare.com/stiri/incendiu/incendiu-puternic-la-o-casa-din-zona-bucurestii-noi-foto-1541199",
            "pub_date": "2018-12-07 12:27:00 GMT",
            "source_nm": "Ziare.com",
            "source_url": "http://www.ziare.com",
            "desc": "Un incendiu a izbucnit, vineri, la o casa de pe strada Vacantei, din Sectorul 1 al Capitalei, in apropierea cartierului Bucurestii Noi. Pompierii actioneaza pentru ..."
        },
        {
            "title": "The Cathedral of the Neam, pleased with additional funds from the City Hall. How much money was allocated to the last rectification - Truth",
            "link": "https://adevarul.ro/news/bucuresti/catedrala-neamului-miluita-fonduri-suplimentare-primaria-capitalei-bani-i-s-au-alocat-ultima-rectificare-1_5c0a2287df52022f75347c21/index.html",
            "pub_date": "2018-12-07 08:13:55 GMT",
            "source_nm": "truth",
            "source_url": "https://adevarul.ro",
            "desc": "Abia inaugurata, Catedrala Mantuirii Neamului va beneficia de inca o alocare substantiala din Partea Primariei Capitalei, suma fiind deja aprobata de Consilul ..."
        },
        {
            "title": "Tragic! A man hit by a tramway car in a STB station - B365.com",
            "link": "http://www.b365.ro/tragic-barbat-lovit-masina-linia-de-tramvai_259983.html",
            "pub_date": "2018-12-07 09:43:00 GMT",
            "source_nm": "B365.ro",
            "source_url": "http://www.b365.ro",
            "desc": "\u015eoferul unui autoturism a circulat, vineri diminea\u0163\u0103, pe linia de tramvai din Bucure\u015fti \u015fi a accidentat un b\u0103rbat de aproximativ 35 de ani c\u00e2nd a ajuns \u00een dreptul ..."
        },
        {
            "title": "Firea wants to give free shipping to all students in Bucharest - Ziare.com",
            "link": "http://www.ziare.com/social/primaria/firea-vrea-sa-dea-gratuitate-la-transport-pentru-toti-elevii-din-bucuresti-1541187",
            "pub_date": "2018-12-07 11:58:00 GMT",
            "source_nm": "Ziare.com",
            "source_url": "http://www.ziare.com",
            "desc": "Elevii din Bucuresti cu varsta de pana la 18 ani ar putea calatori gratuit cu mijloacele de transport in comun ale STB (fosta RATB), potrivit unui proiect al ..."
        },
        {
            "title": "The final of the Romanian PUBG League is held on Sunday at Bucharest Gaming Week - Adev\u0103rul",
            "link": "https://adevarul.ro/tech/gaming/finala-ligii-romanesti-pubg-loc-duminica-cadrul-bucharest-gaming-week-1_5c0a8076df52022f75373457/index.html",
            "pub_date": "2018-12-07 14:18:40 GMT",
            "source_nm": "truth",
            "source_url": "https://adevarul.ro",
            "desc": "Finala Sezonului 2 a Ligii Rom\u00e2niei de Playerunknown's Battlegrounds va avea loc \u00een cadrul evenimentului Bucharest Gaming Week, \u00een weekend-ul 8-9 ..."
        },
        {
            "title": "Fallen houses 274 - Str. Vasile Alecsandri 6 - Metropotam",
            "link": "http://metropotam.ro/La-zi/Case-cazute-274-Str-Vasile-Alecsandri-6-art7827356142/",
            "pub_date": "2018-12-08 11:16:31 GMT",
            "source_nm": "Metropotam",
            "source_url": "http://metropotam.ro",
            "desc": "Articol preluat de pe blogul Simply Bucharest . scris de Ando Sper, sincer, s\u0103 nu fiu piaz\u0103-rea! De c\u00e2\u0163iva ani, de c\u00e2te ori trec pe aici, aceast\u0103 cl\u0103dire \u00eemi pare din ..."
        },
        {
            "title": "Nexus Gaming Romanians Play Counter Strike Global Offensive Final This Weekend at Bucharest Gaming Week - GadgetZone.com",
            "link": "https://www.gadgetzone.ro/romanii-de-la-nexus-gaming-joaca-finala-de-counter-strike-global-offensive-acest-weekend-la-bucharest-gaming-week/",
            "pub_date": "2018-12-07 21:39:59 GMT",
            "source_nm": "GadgetZone.ro",
            "source_url": "https://www.gadgetzone.ro",
            "desc": "Nu \u015ftiu dac\u0103 sunte\u0163i la curent, dar ne afl\u0103m \u00een plin\u0103 s\u0103pt\u0103m\u00e2n\u0103 de Bucharest Gaming Week 2018. Este o serie de evenimente, prezent\u0103ri, conferin\u0163e \u015fi expozi\u0163ii ..."
        },
        {
            "title": "The mute parrot - Nearly true stories about a spy - Metropotam",
            "link": "http://metropotam.ro/evenimente/Papagalul-mut-Istorii-aproape-adevarate-despre-un-spion-event1592694602/",
            "pub_date": "2018-12-08 11:12:36 GMT",
            "source_nm": "Metropotam",
            "source_url": "http://metropotam.ro",
            "desc": "Afla detalii despre Papagalul mut - Istorii aproape adevarate despre un spion Piese-de-teatru din Teatrul National Bucuresti, Bucuresti, 08 Dec 2018 19:00 - 09 ..."
        },
        {
            "title": "Trams are blocked on Stefan cel Mare Road in Bucharest after an accident - Ziare.com",
            "link": "http://www.ziare.com/stiri/accident/tramvaiele-sunt-blocate-pe-soseaua-stefan-cel-mare-din-bucuresti-dupa-un-accident-1541154",
            "pub_date": "2018-12-07 08:16:00 GMT",
            "source_nm": "Ziare.com",
            "source_url": "http://www.ziare.com",
            "desc": "Circulatia tramvaielor este blocata, vineri dimineata, in zona statiei Dr. Grozovici din Capitala pe sensul catre Obor, in urma unui accident."
        },
        {
            "title": "The History Boys. Story with high school perfume - Metropotam",
            "link": "http://metropotam.ro/evenimente/The-History-Boys-Povesti-cu-parfum-de-liceu-event2229724313/",
            "pub_date": "2018-12-08 12:19:38 GMT",
            "source_nm": "Metropotam",
            "source_url": "http://metropotam.ro",
            "desc": "Afla detalii despre The History Boys. Povesti cu parfum de liceu Piese-de-teatru din Excelsior, Bucuresti, 10 Dec 2018 18:30."
        },
        {
            "title": "Arts start in Bucharest - the first exhibition dedicated to families and couples of artists - Garbo",
            "link": "https://www.garbo.ro/articol/Noutati/24378/arte-in-bucuresti-2018.html",
            "pub_date": "2018-12-07 10:44:24 GMT",
            "source_nm": "Garbo",
            "source_url": "https://www.garbo.ro",
            "desc": "Arte in Bucuresti 2018, eveniment organizat de Uniunea Artistilor Plastici din Romania si sustinut de Primaria Municipiului Bucuresti prin Expo Arte, debuteaza."
        },
        {
            "title": "Fierce loses one more time in court: Court suspended decisions to dismantle 4 administrations in Bucharest - Ziare.com",
            "link": "http://www.ziare.com/gabriela-firea/primar-bucuresti/firea-mai-pierde-o-data-in-instanta-tribunalul-a-suspendat-hotararile-prin-care-erau-desfiintate-4-administratii-din-bucuresti-1541270",
            "pub_date": "2018-12-08 05:00:00 GMT",
            "source_nm": "Ziare.com",
            "source_url": "http://www.ziare.com",
            "desc": "Tribunalul Bucuresti a decis, vineri, sa suspende hotararile de Consiliu General prin care erau desfiintate patru administratii din Bucuresti pentru a face loc ..."
        },
        {
            "title": "In front of the National Bank of Bucharest, huge queues have been formed for the special centenary banknote - ZIUA of Constanta",
            "link": "https://www.ziuaconstanta.ro/diverse/stiri-calde/in-fata-bancii-nationale-din-bucuresti-s-au-format-cozi-imense-pentru-bancnota-speciala-de-centenar-678620.html",
            "pub_date": "2018-12-07 19:56:00 GMT",
            "source_nm": "DAY from Constanta",
            "source_url": "https://www.ziuaconstanta.ro",
            "desc": "La ora 10 diminea\u0163a, peste 200 de oameni a\u015fteptau \u00een fa\u0163a B\u0103ncii Na\u0163ionale, s\u0103 cumpere bancnota de o sut\u0103 de lei, cu regina Maria \u015fi regele Ferdinand, \u00een edi\u0163ie ..."
        },
        {
            "title": "Agglomeration on the subway due to a new fault - Truth",
            "link": "https://adevarul.ro/news/bucuresti/aglomeratie-metrou-cauza-defectiuni-1_5c0a2febdf52022f7534dc4c/index.html",
            "pub_date": "2018-12-07 08:33:45 GMT",
            "source_nm": "truth",
            "source_url": "https://adevarul.ro",
            "desc": "A fost aglomeratie vineri dimineata la metrou din cauza unei defectiuni tehnice. Trenul a ajuns cu intarziere la Piata Victoriei."
        },
        {
            "title": "Bucharest City Hall wants students in Bucharest to travel for free with public transport - SuperBEBE.ro",
            "link": "https://superbebe.ro/stiri/primaria-capitalei-vrea-ca-elevii-din-bucuresti-sa-calatoreasca-gratuit-cu-transportul-public/",
            "pub_date": "2018-12-07 15:08:12 GMT",
            "source_nm": "SuperBEBE.ro",
            "source_url": "https://superbebe.ro",
            "desc": "Primaria Capitalei vrea ca elevii din Bucuresti sa calatoreasca gratuit cu transportul public. Elevii din Bucuresti cu varsta de pana la 18 ani ar putea calatori ..."
        },
        {
            "title": "100 doctors to receive money from Bucharest City Hall to go to courses in Europe, USA or Israel - Business24.ro",
            "link": "http://www.business24.ro/administratie/stiri-administratie/100-de-medici-vor-primi-bani-de-la-primaria-bucuresti-ca-sa-mearga-la-cursuri-in-europa-sua-sau-israel-1599876",
            "pub_date": "2018-12-07 14:37:00 GMT",
            "source_nm": "Business24.ro",
            "source_url": "http://www.business24.ro",
            "desc": "100 de medici din Capitala, angajati in spitalele din subordinea ASSMB, vor primi vouchere de 10.000 de lei, in anul 2019, pentru participarea la cursuri ..."
        },
        {
            "title": "Bucharest, Cluj and Timi\u015foara among the 2,800 localities that will offer free Wi-Fi with EU money - EurActiv",
            "link": "https://www.euractiv.ro/social/bucuresti-cluj-si-timisoara-printre-cele-2.800-localitati-care-vor-oferi-wi-fi-gratuit-cu-bani-ue-12865",
            "pub_date": "2018-12-07 12:35:45 GMT",
            "source_nm": "EurActiv",
            "source_url": "https://www.euractiv.ro",
            "desc": "Pe lista localit\u0103\u0163ilor selec\u0163ionate se afl\u0103 \u015fi alte ora\u015fe \u015fi comune din Rom\u00e2nia. Fiecare localitate va primi un voucher \u00een valoare de 15.000 de euro pentru ..."
        },
        {
            "title": "Fire at a household in Bucharest. The fire extends in the surroundings (photo gallery + video) - ZIUA de Constanta",
            "link": "https://www.ziuaconstanta.ro/diverse/stiri-calde/incendiu-la-o-gospodarie-din-bucuresti-incendiul-se-extinde-si-in-imprejurimi-678570.html",
            "pub_date": "2018-12-07 12:28:00 GMT",
            "source_nm": "DAY from Constanta",
            "source_url": "https://www.ziuaconstanta.ro",
            "desc": "Pompierii din cadrul ISU Bucure\u015fti-Ilfov intervin vineri dup\u0103-amiaz\u0103 pe strada Vacan\u0163ei din Capital\u0103. Incendiul se manifest\u0103 la o cas\u0103 \u015fi la anexele gospod\u0103re\u015fti."
        },
        {
            "title": "Maternity Giulesti could be relocated. The People&#39;s Advocate has noticed ex officio in the case of infected children with gold staphylococcus - The Truth",
            "link": "https://adevarul.ro/news/societate/maternitatea-giulesti-putea-relocata-avocatul-poporului-s-a-sesizat-oficiu-cazul-bebelusilor-infectati-stafilococ-auriu-1_5c0a7dc5df52022f75371e1c/index.html",
            "pub_date": "2018-12-07 14:25:14 GMT",
            "source_nm": "truth",
            "source_url": "https://adevarul.ro",
            "desc": "Maternitatea Giule\u015fti ar putea fi relocat\u0103, potrivit unui proiect al Administra\u0163iei Spitalelor \u015fi Serviciilor Medicale Bucure\u015fti (ASSMB). Asta dup\u0103 ce 23 de bebelu\u015fi ..."
        },
        {
            "title": "The problems of schools in Bucharest: dirty toilets, lack of sports halls, misery - Reality",
            "link": "https://www.realitatea.net/problemele-scolilor-din-bucuresti-toalete-murdare-lipsa-salilor-de-sport-mizerie_2173064.html",
            "pub_date": "2018-12-07 10:10:14 GMT",
            "source_nm": "The reality",
            "source_url": "https://www.realitatea.net",
            "desc": "Cele mai mari probleme ale \u015fcolilor bucure\u015ftene, \u00een viziunea p\u0103rin\u0163ilor, sunt mizeria de la toalete, absen\u0163a s\u0103lilor de sport, mizeria din \u0219coal\u0103 sau din curtea ..."
        },
        {
            "title": "A cyclist died in a road accident on the Road. Bucharest-Targoviste - Reality",
            "link": "https://m.realitatea.net/un-biciclist-a-decedat-pe-loc-intr-un-accident-rutier-pe-sos-bucuresti-targoviste_2172995.html",
            "pub_date": "2018-12-06 16:25:38 GMT",
            "source_nm": "The reality",
            "source_url": "https://m.realitatea.net",
            "desc": "comentarii, Un biciclist a decedat pe loc \u00eentr-un accident ce a avut loc pe \u015eos. Bucure\u015fti-T\u00e2rgovi\u015fte, fiind implicat un autotractor, informeaz\u0103 Brigada rutier\u0103 a ..."
        },
        {
            "title": "The Demirkaya case, Turkish refugee journalist in Bucharest, and the Romanian state - Ziare.com",
            "link": "http://www.ziare.com/stiri/politie/cazul-demirkaya-jurnalist-turc-refugiat-la-bucuresti-si-statul-roman-1541096",
            "pub_date": "2018-12-06 15:46:00 GMT",
            "source_nm": "Ziare.com",
            "source_url": "http://www.ziare.com",
            "desc": "Stau si dardai. Dar nu de frig. E cald aici, in camera. Si-n vestul Europei. Crivatul din Rusia vine. Iar cel politic si din Turcia, dar si, mai nou, din Romania ..."
        },
        {
            "title": "Project: 10,000 lei vouchers for companies wanting to set up electric charging stations in the capital - G4Media.ro",
            "link": "https://www.g4media.ro/proiect-vouchere-de-10-mii-de-lei-pentru-firmele-care-vor-sa-infiinteze-statii-de-incarcare-electrice-in-capitala.html",
            "pub_date": "2018-12-07 10:40:45 GMT",
            "source_nm": "G4Media.ro",
            "source_url": "https://www.g4media.ro",
            "desc": "Pe ordinea de zi a \u0219edin\u021bei Consiliului General al Municipiului Bucure\u0219ti, programat\u0103 pentru data de 12 decembrie, se afl\u0103 un proiect ALDE, care propune."
        },
        {
            "title": "Massive fire in Bucharesti Noi - Secunda TV",
            "link": "http://www.secundatv.ro/social/incendiu-de-proportii-in-cartierul-bucurestii-noi-126822.html/",
            "pub_date": "2018-12-07 12:28:00 GMT",
            "source_nm": "Second TV",
            "source_url": "http://www.secundatv.ro",
            "desc": "Un incendiu de propor\u021bii a izbucnit, vineri dup\u0103-amiaz\u0103, \u00een cartierul Bucure\u0219tii Noi. Incendiul a izbucnit la o cas\u0103 situat\u0103 pe Strada Vacan\u021bei \u0219i s-a extins la un ..."
        },
        {
            "title": "Calvary on the Bucharest subway, Friday morning. As a &quot;reward&quot;, the trip is expensive - Reality",
            "link": "https://m.realitatea.net/calvar-la-metroul-bucurestean_2173040.html",
            "pub_date": "2018-12-07 06:48:44 GMT",
            "source_nm": "The reality",
            "source_url": "https://m.realitatea.net",
            "desc": "comentarii, Bucure\u015ftenii care au c\u0103l\u0103torit cu metroul vineri diminea\u0163\u0103 s-au confruntat din nou cu calvarul., stiri, realitatea.net."
        },
        {
            "title": "PSD, forced by the Bucharest Tribunal to say how much the trial against the &quot;abuses in justice&quot; of 9 June cost - Adev\u0103rul",
            "link": "https://adevarul.ro/news/eveniment/psd-obligat-tribunalul-bucuresti-spuna-costat-mitingul-abuzurilor-justitie-9-iunie-1_5c093f63df52022f752f9a64/index.html",
            "pub_date": "2018-12-06 16:01:25 GMT",
            "source_nm": "truth",
            "source_url": "https://adevarul.ro",
            "desc": "Tribunalul Bucure\u015fti a decis joi c\u0103 PSD trebuie s\u0103 fac\u0103 publice informa\u0163iile privind costurile organiz\u0103rii mitingului \u00eempotriva \u201eabuzurilor din justi\u0163ie\u201d din 9 iunie, din ..."
        },
        {
            "title": "Incident at a club known in Bucharest, fell pieces of plaster - Reality",
            "link": "https://www.realitatea.net/incident-la-un-club-cunoscut-din-bucuresti-au-cazut-bucati-de-tavan_2172955.html",
            "pub_date": "2018-12-05 08:00:00 GMT",
            "source_nm": "The reality",
            "source_url": "https://www.realitatea.net",
            "desc": "Incident miercuri sear\u0103, \u00eentr-unul dintre cele mai cunoscute loca\u0163ii de muzic\u0103 live din Capital\u0103, Clubul Control. Mai multe buc\u0103\u0163i de tencuial\u0103 din tavan au c\u0103zut ..."
        },
        {
            "title": "The RAC refuses to abide by a final court ruling. Denial that could hide a serious crime - Ziare.com",
            "link": "http://www.ziare.com/articole/ccr+nu+respecta+hotararea+cab",
            "pub_date": "2018-12-07 22:00:00 GMT",
            "source_nm": "Ziare.com",
            "source_url": "http://www.ziare.com",
            "desc": "CCR continua sa refuze sa respecte o hotarare judecatoreasca definitiva, care o obliga sa respecte un drept constitutional fundamental, dreptul la libera ..."
        },
        {
            "title": "Centenar Radu Beligan - Secunda TV",
            "link": "http://www.secundatv.ro/teatru-muzica-si-film/centenar-radu-beligan-126897.html/",
            "pub_date": "2018-12-08 09:25:00 GMT",
            "source_nm": "Second TV",
            "source_url": "http://www.secundatv.ro",
            "desc": "La exact 100 de ani de la na\u0219terea lui Radu Beligan, pe 14 decembrie, \u00eencep\u00e2nd cu ora 17.00, Teatrul Na\u021bional Bucure\u0219ti, \u00een parteneriat cu Prim\u0103ria Capitalei ..."
        },
        {
            "title": "German choruses on the stage of the Excelsior Awards Gala - Neamt and Roman Monitor",
            "link": "http://monitorulneamt.ro/coruri-nemtene-pe-scena-galei-premiilor-excelsior/",
            "pub_date": "2018-12-08 04:16:25 GMT",
            "source_nm": "Monitorul de Neamt and Roman",
            "source_url": "http://monitorulneamt.ro",
            "desc": "... \u25a1 dou\u0103 forma\u0163ii corale din jude\u0163ul Neam\u0163 vor concerta la Bucure\u015fti, la invita\u0163ia Prim\u0103riei Capitalei \u25a1 evenimentul va fi transmis \u00een direct de TVR \u25a1 nem\u0163enii ..."
        },
        {
            "title": "Director of the Gulliver Theater, awarded in Bucharest - Life Free Gala\u0163i - Free Life",
            "link": "https://www.viata-libera.ro/vlg-cultura/119553-directortul-teatrului-gulliver-premiat-la-bucuresti",
            "pub_date": "2018-12-06 13:00:00 GMT",
            "source_nm": "Free life",
            "source_url": "https://www.viata-libera.ro",
            "desc": "La edi\u0163ia din acest an a Festivalului Interna\u0163ional al Teatrului Contemporan de Anima\u0163ie ImPuls, organizat de Teatrul \"\u0162\u0103nd\u0103ric\u0103\", Premiul pentru mana..."
        },
        {
            "title": "Premiere at TNB! The mute parrot - Nearly true stories about a nearly forgotten spy - Second TV",
            "link": "http://www.secundatv.ro/teatru-muzica-si-film/premiera-la-tnb-papagalul-mut-istorii-aproape-adevarate-despre-un-spion-aproape-uitat-126883.html/",
            "pub_date": "2018-12-08 09:03:00 GMT",
            "source_nm": "Second TV",
            "source_url": "http://www.secundatv.ro",
            "desc": "Unul din cei mai cunoscu\u0163i regizori rom\u00e2ni de film, multi-premiatul Nae Caranfil, dup\u0103 trei decenii de la debutul s\u0103u \u00een cinematografie, se afl\u0103 la acest final de ..."
        },
        {
            "title": "RADET disaster in Bucharest: Hundreds of buildings without heat and hot water, due to damage - Realitatea",
            "link": "https://m.realitatea.net/dezastrul-radet-in-bucure-ti-sute-de-cladiri-fara-caldura-i-apa-calda-din-cauza-avariilor_2172935.html",
            "pub_date": "2018-12-06 10:09:24 GMT",
            "source_nm": "The reality",
            "source_url": "https://m.realitatea.net",
            "desc": "comentarii, Sute de cl\u0103diri din sectoarele 2, 3, 4, 5 \u0219i 6 ale Bucure\u0219tiului st\u0103teau f\u0103r\u0103 ap\u0103 cald\u0103 \u0219i/sau c\u0103ldur\u0103, joi, din cauza avariilor ap\u0103rute \u00een re\u021beaua de ..."
        },
        {
            "title": "Vlad Casino and The Codex open the biggest escape room in ... - B365.ro",
            "link": "http://www.b365.ro/vlad-cazino-si-the-codex-deschid-cel-mai-mare-escape-room-din-bucuresti_259979.html",
            "pub_date": "2018-12-06 12:05:00 GMT",
            "source_nm": "B365.ro",
            "source_url": "http://www.b365.ro",
            "desc": "The Codex deschide cea mai noua si mai mare camera de escape room din Bucuresti, iar povestea ei este strans legata de cea a lui Vlad Intuneceanu \u2013 cel mai ..."
        },
        {
            "title": "Striking Assistant at the University Hospital, serious accusations against the Government - Reality",
            "link": "https://m.realitatea.net/asistenta-grevista-de-la-spitalul-universitar-acuza-ii-grave-la-adrsa-guvernului_2173175.html",
            "pub_date": "2018-12-08 07:13:56 GMT",
            "source_nm": "The reality",
            "source_url": "https://m.realitatea.net",
            "desc": "comentarii, Asistenta grevist\u0103 de la Spitalul Universitar, concediat\u0103 \u00een octombrie, spune c\u0103 haosul din unitatea spitaliceasc\u0103 a \u00eenceput dup\u0103 ce la conducere a ..."
        },
        {
            "title": "Gala 5 high schools 5 theaters - ecomunicate.ro",
            "link": "https://www.ecomunicate.ro/comunicat/gala-5-licee-5-teatre/",
            "pub_date": "2018-12-07 19:30:00 GMT",
            "source_nm": "ecomunicate.ro",
            "source_url": "https://www.ecomunicate.ro",
            "desc": "Luni, 10 decembrie 2018, incepand cu ora 17:00, la Sala Majestic a Teatrului Odeon, va avea loc Gala 5 licee - 5 teatre, aflata anul acesta la editia a 8-a."
        },
        {
            "title": "MAI headquarters will be rehabilitated and modernized with over 322 million lei - Business24.ro",
            "link": "http://www.business24.ro/guvern/stiri-guvern/sediul-mai-va-fi-reabilitat-si-modernizat-cu-peste-322-milioane-de-lei-1599875",
            "pub_date": "2018-12-07 14:19:00 GMT",
            "source_nm": "Business24.ro",
            "source_url": "http://www.business24.ro",
            "desc": "Sediul Ministerului Afacerilor Interne din Piata Revolutiei, contruit in 1940, va fi reabilitat si modernizat, valoarea totala a investitiei fiind de peste 322 de milioane ..."
        },
        {
            "title": "Bucharest included in the Colt IQ Network - IT &amp; C Club",
            "link": "http://www.clubitc.ro/2018/12/06/colt-include-bucurestiul-in-extinderea-retelei-de-banda-larga-iq-network-in-regiunea-cee/",
            "pub_date": "2018-12-06 10:55:07 GMT",
            "source_nm": "Club IT &amp; C",
            "source_url": "http://www.clubitc.ro",
            "desc": "Colt Technology Services extinde re\u021beau sa global\u0103 Colt IQ Network \u00een Europa Centrala \u0219i de Est, \u00eencuraj\u00e2nd astfel transformarea digital\u0103 a companiilor din ..."
        },
        {
            "title": "Wise Finance Solutions and Human Resocia announce a European recruitment program for IT graduates in Japan - Business24.ro",
            "link": "http://www.business24.ro/locuri-de-munca/locuri-munca-in-strainatate/wise-finance-solutions-si-human-resocia-anunta-un-program-european-de-recrutare-a-absolventilor-de-it-in-japonia-1599866",
            "pub_date": "2018-12-07 11:51:00 GMT",
            "source_nm": "Business24.ro",
            "source_url": "http://www.business24.ro",
            "desc": "Wise Finance Solutions, companie de consultanta in atragerea fondurilor europene si a ajutoarelor de stat, anunta parteneriatul cu Human Resocia, un mare ..."
        },
        {
            "title": "Romania 100 &amp; Israel 70: Inauguration of the Jerusalem Lion Square with the homonym statue and the Academician Nicolae Cajal - Ziare.com",
            "link": "http://www.ziare.com/scoala/educatie/romania-100-israel-70-inaugurarea-pietei-leul-ierusalimului-cu-statuia-omonima-si-a-cladirii-academician-nicolae-cajal-1541086",
            "pub_date": "2018-12-06 14:51:00 GMT",
            "source_nm": "Ziare.com",
            "source_url": "http://www.ziare.com",
            "desc": "Primaria Municipiului Bucuresti, prin Administratia Monumentelor si Patrimoniului Turistic, Primaria Sectorului 3, in colaborare cu Ambasada Israelului in ..."
        },
        {
            "title": "The Jewish Film Festival takes place December 13-16 in Bucharest - B365.ro",
            "link": "http://www.b365.ro/festivalul-de-film-evreiesc-are-loc-intre-13-16-decembrie-la-bucuresti_259974.html",
            "pub_date": "2018-12-06 07:40:00 GMT",
            "source_nm": "B365.ro",
            "source_url": "http://www.b365.ro",
            "desc": "Festivalul de Film Evreiesc, editia a opta, revine la Bucuresti pe 13 decembrie, cu o selectie de opere inedite cinematografice semnate de regizori evrei de ..."
        },
        {
            "title": "Mircea Draghici Seeks Judicial Inspection after General Prosecution Announces Criminal Investigation for How He Spent Over Half a Million Euro of Public Money Received by PSD - G4Media.ro",
            "link": "https://www.g4media.ro/mircea-draghici-a-sesizat-inspectia-judiciara-dupa-ce-parchetul-general-a-anuntat-ca-il-cerceteaza-penal-pentru-modul-in-care-a-cheltuit-peste-jumatate-de-milion-de-euro-din-banii-publici-primiti-de-p.html",
            "pub_date": "2018-12-06 15:56:38 GMT",
            "source_nm": "G4Media.ro",
            "source_url": "https://www.g4media.ro",
            "desc": "Trezorierul PSD, deputatul Mircea Dr\u0103ghici, a anun\u0163at joi c\u0103 a sesizat Inspec\u0163ia Judiciar\u0103 cu privire la \"abaterile disciplinare\" s\u0103v\u00e2r\u015fite de procurorii."
        },
        {
            "title": "Strong fire in Bucharest New. Hydrants do not work - Reality",
            "link": "https://m.realitatea.net/incendiu-in-bucurestii-noi_2173086.html",
            "pub_date": "2018-12-07 12:27:12 GMT",
            "source_nm": "The reality",
            "source_url": "https://m.realitatea.net",
            "desc": "comentarii, Pompierii intervin cu mai multe autospeciale la un incendiu din Bucure\u015ftii Noi, la dou\u0103 case dintr-un cartier cu mai multe locuin\u0163e. , stiri, ..."
        },
        {
            "title": "Road Traffic Police Checks in Bucharest: 10% of the checked cars had major technical failures - Truth",
            "link": "https://adevarul.ro/news/bucuresti/controale-politiei-rutiere-taximetristii-bucuresti-10-autoturismele-verificate-aveau-defectiuni-tehnice-majore-1_5c08b838df52022f752b97ef/index.html",
            "pub_date": "2018-12-06 05:51:51 GMT",
            "source_nm": "truth",
            "source_url": "https://adevarul.ro",
            "desc": "Poli\u0163i\u015ftii de la Brigada Rutier\u0103 au re\u0163inut \u015fase permise \u015fi au dat amenzi \u00een valoare de 32.000 de lei \u00een dou\u0103 zile de controale care au vizat 158 de taxiuri din ..."
        },
        {
            "title": "Presidential Education Report - Lucian Ciolan, Dean of the Faculty of Education Sciences: Strategies are not made by referendum. I assume there will be a science-based work - G4Media.ro",
            "link": "https://www.g4media.ro/raportul-prezidential-pe-educatie-lucian-ciolan-decanul-facultatii-de-stiintele-educatiei-strategiile-nu-se-fac-prin-referendum-presupun-ca-se-va-trece-la-o-munca-bazata-pe-stiinta.html",
            "pub_date": "2018-12-07 09:04:51 GMT",
            "source_nm": "G4Media.ro",
            "source_url": "https://www.g4media.ro",
            "desc": "Raportul preziden\u021bial pe educa\u021bie are nevoie de o etap\u0103 \u201cbazat\u0103 mai mult pe \u0219tiin\u021b\u0103 \u0219i mai pu\u021bin pe opiniile maselor largi de oameni\u201d. \u201c\u00cen toat\u0103 lumea,"
        },
        {
            "title": "10% of the taxi in Bucharest checked by police officers have major technical failures - Business24.ro",
            "link": "http://www.business24.ro/administratie/stiri-administratie/10-la-suta-dintre-taxiurile-din-bucuresti-verificate-de-politisti-au-defectiuni-tehnice-majore-1599819",
            "pub_date": "2018-12-06 09:22:00 GMT",
            "source_nm": "Business24.ro",
            "source_url": "http://www.business24.ro",
            "desc": "Politistii de la Brigada Rutiera au facut controale la taxiuri, rezultand ca 10% dintre masinile verificate au defectiuni tehnice majore."
        },
        {
            "title": "Taxify introduces fixed tariff in Bucharest - Passengers will have the price of the race before calling a car - Mobile Communications",
            "link": "http://www.comunic.ro/article/taxify-introduce-tariful-fix-%C3%AEn-bucure%C8%99ti-pasagerii-vor-avea-pre%C8%9Bul-cursei-%C3%AEnainte-de-chema",
            "pub_date": "2018-12-06 08:44:03 GMT",
            "source_nm": "Mobile Communications",
            "source_url": "http://www.comunic.ro",
            "desc": "Taxify, cea mai mare platform\u0103 european\u0103 de ride-hailing, introduce tariful fix \u00een Bucure\u0219ti. Astfel, pasagerii vor \u0219ti pre\u021bul cursei \u00eenainte de a chema o ma\u0219in\u0103."
        },
        {
            "title": "PMB announces another 2,000 couples benefits from financial support for in vitro fertilization - B365.ro",
            "link": "http://www.b365.ro/pmb-anunta-alte-2-000-de-cupluri-beneficiaza-de-sprijin-financiar-pentru-fertilizare-in-vitro_259976.html",
            "pub_date": "2018-12-06 08:23:00 GMT",
            "source_nm": "B365.ro",
            "source_url": "http://www.b365.ro",
            "desc": "Primaria Capitalei anunta ca initiaza a doua etapa a proiectului \"O sansa pentru cuplurile infertile\"- FIV 2, alte 2.000 de cupluri urm\u00e2nd sa beneficieze de sprijin ..."
        },
        {
            "title": "Deputy from Bucharest: &quot;Romania, sponsored by Plaha; Tariceanu, Dragnea and Candu decorate each other! &quot;- jurnal.md",
            "link": "http://jurnal.md/ro/news/f0af36133815ea98/deputat-de-la-bucuresti-romania-sponsored-by-plaha-tariceanu-dragnea-si-candu-se-decoreaza-reciproc.html",
            "pub_date": "2018-12-07 11:08:27 GMT",
            "source_nm": "jurnal.md",
            "source_url": "http://jurnal.md",
            "desc": "\u201eDou\u0103 evenimente recente ilustreaz\u0103 foarte bine starea de fapt p\u0103guboas\u0103 \u00een care ne afl\u0103m. Pre\u0219edintele Parlamentului moldovean, Andrian Candu, a fost ..."
        },
        {
            "title": "Notarra Theater in Bucharest to present Marin Sorescu show at Latina Ginta - radiochisinau.md",
            "link": "https://radiochisinau.md/teatrul-notarra-din-bucuresti-va-prezenta-un-spectacol-demarin-sorescu-la-ginta-latina---79070.html?fbrefresh=1544118530",
            "pub_date": "2018-12-07 05:44:00 GMT",
            "source_nm": "radiochisinau.md",
            "source_url": "https://radiochisinau.md",
            "desc": "La teatrul de revist\u0103 Ginta Latin\u0103 din Chi\u0219in\u0103u a sosit echipa teatrului Nottara din Bucure\u0219ti, care va prezenta vineri, 7 decembrie, la 15.00 \u0219i la 19.00, ..."
        },
        {
            "title": "VIDEOCustom in Bucharest, on the Olteni\u0163a Road, at a warehouse - Realitatea",
            "link": "https://m.realitatea.net/incendiu-puternic-in-bucure-ti-pe-oseaua-olteni-ei_2172873.html",
            "pub_date": "2018-12-05 18:57:16 GMT",
            "source_nm": "The reality",
            "source_url": "https://m.realitatea.net",
            "desc": "comentarii, Un incendiu masiv a fost semnalat la 112, la care a intervenit ISU Bucure\u0219ti - Ilfov, miercuri seara! Conform primelor informa\u021bii, fl\u0103c\u0103rile au cuprins o ..."
        },
        {
            "title": "Bucharest, who murdered his wife right in her kindergarten, was sentenced to life imprisonment - Adev\u0103rul",
            "link": "https://adevarul.ro/news/bucuresti/bucuresteanul-si-a-ucis-sotia-gradinita-conducea-fost-condamnat-inchisoare-viata-1_5c094d89df52022f752ffb29/index.html",
            "pub_date": "2018-12-06 16:56:00 GMT",
            "source_nm": "truth",
            "source_url": "https://adevarul.ro",
            "desc": "Magistratii Tribunalului Bucuresti l-au condamnat la inchisoare pe viata pe sotul directoarei de gradinita, acuzat ca, la inceputul anului, a injunghiat-o pe aceasta ..."
        },
        {
            "title": "Socor: Bucharest Power Makes Plahotniuc Serving Funding Sites Opposing Opposition - cotidianul.md",
            "link": "https://cotidianul.md/2018/12/07/socor-puterea-de-la-bucuresti-ii-face-un-serviciu-lui-plahotniuc-finantand-site-uri-care-ataca-opozitia/",
            "pub_date": "2018-12-07 10:41:31 GMT",
            "source_nm": "cotidianul.md",
            "source_url": "https://cotidianul.md",
            "desc": "Actuala putere de la Bucure\u0219ti continu\u0103 s\u0103-i fac\u0103 servicii liderului PD, Vladimir Plahotniuc, inclusiv prin finan\u021barea unor publica\u021bii de la Chi\u0219in\u0103u care atac\u0103 ..."
        },
        {
            "title": "Training course in speech therapy: 23 FEB. 2019 - ecomunicate.ro",
            "link": "https://www.ecomunicate.ro/comunicat/curs-formare-in-logopedie-23-feb-2019/",
            "pub_date": "2018-12-07 19:29:00 GMT",
            "source_nm": "ecomunicate.ro",
            "source_url": "https://www.ecomunicate.ro",
            "desc": "RASG Cluj in colaborare cu Clinica Aquamarin organizeaza in Bucuresti urmatorul curs de formare continua: DIAGNOSTIC, EVALUARE SI INTERVENTIE IN ..."
        },
        {
            "title": "Bassarabia Rock Winter in Club Quantic - TICKETS - INFOMUSIC",
            "link": "https://www.infomusic.ro/agenda/basarabia-rock-winter-concert-quantic-2018/",
            "pub_date": "2018-12-07 11:24:55 GMT",
            "source_nm": "INFOMUSIC",
            "source_url": "https://www.infomusic.ro",
            "desc": "Evenimentul \"Basarabia Rock Winter\" are loc \u00een Club Quantic pe 13 decembrie 2018. Detalii despre trupe \u0219i bilete \u00een articol."
        },
        {
            "title": "AOR, ACoR and AMR urge minister of finance to stop freezing jobs in local administration - ZIUA of Constanta",
            "link": "https://www.ziuaconstanta.ro/stiri/administratie-locala/aor-acor-si-amr-solicita-ministrului-finantelor-sa-renunte-la-inghetarea-angajarilor-in-administratia-locala-678618.html",
            "pub_date": "2018-12-07 22:00:00 GMT",
            "source_nm": "DAY from Constanta",
            "source_url": "https://www.ziuaconstanta.ro",
            "desc": "Asociatia Oraselor din Romania AOR , alaturi de Asociatia Comunelor din Romania ACoR si Asociatia Municipiilor din Romania AMR , i-a solicitat lui ..."
        },
        {
            "title": "Dangerous incident in one of the biggest clubs in Bucharest: A piece of ceiling collapsed (Video) - Ziare.com",
            "link": "http://www.ziare.com/stiri/eveniment/incident-periculos-intr-unul-dintre-cele-mai-mari-cluburi-din-bucuresti-s-a-prabusit-o-bucata-de-tavan-video-1541064",
            "pub_date": "2018-12-06 13:21:00 GMT",
            "source_nm": "Ziare.com",
            "source_url": "http://www.ziare.com",
            "desc": "Bucati de tencuiala din tavanul Clubului Control din Bucuresti s-au prabusit miercuri seara. Reprezentantii localului sustin ca ''au cazut doua bucati de tencuiala ..."
        },
        {
            "title": "Working with the drawing in psychotherapy: 25 Jan. 2019 - ecomunicate.ro",
            "link": "https://www.ecomunicate.ro/comunicat/lucrul-cu-desenul-in-psihoterapie-25-ian-2019/",
            "pub_date": "2018-12-07 19:29:00 GMT",
            "source_nm": "ecomunicate.ro",
            "source_url": "https://www.ecomunicate.ro",
            "desc": "Workshop in care vei invata sa descoperi personalitatea cuiva cu ajutorul desenului pe care acesta l-a facut."
        },
        {
            "title": "The Book of Jungle - The Magic of the Musical Performance in Bucharest - TICKETS - INFOMUSIC",
            "link": "https://www.infomusic.ro/agenda/cartea-junglei-musical-bucuresti-decembrie-2018/",
            "pub_date": "2018-12-05 16:23:14 GMT",
            "source_nm": "INFOMUSIC",
            "source_url": "https://www.infomusic.ro",
            "desc": "Cartea Junglei prinde via\u021b\u0103 printr-un spectacol musical ce va avea loc la Palatul Na\u021bional al Copiilor din Bucure\u0219ti pe 11 \u0219i 12 decembrie 2018."
        },
        {
            "title": "PHOTO. Rubix, the robotics team of &quot;IM Clain&quot; Blaj College, enrolled in BRD First Tech Challenge Romania. He has earned 5,000 euros, and in five months the robot has to be built - the Unirea newspaper",
            "link": "https://ziarulunirea.ro/foto-rubix-echipa-de-robotica-a-colegiului-i-m-clain-blaj-inscrisa-in-competitia-brd-first-tech-challenge-romania-a-obtinut-5-000-de-euro-iar-in-cinci-luni-trebuie-construit-r-502892/",
            "pub_date": "2018-12-08 08:46:03 GMT",
            "source_nm": "Unirea newspaper",
            "source_url": "https://ziarulunirea.ro",
            "desc": "\u00cen societatea contemporan\u0103 este necesar s\u0103 se investeasc\u0103 \u00een capitalul uman prin educa\u021bie STEM (un acronim care vine de la cuvintele engleze\u015fti Science, ..."
        },
        {
            "title": "Five men in red who terrorized Pantelimon one night - Truth",
            "link": "https://adevarul.ro/news/bucuresti/cinci-barbati-rosu-terorizat-pantelimonul-intr-o-seara-1_5c0a30efdf52022f7534e38f/index.html",
            "pub_date": "2018-12-07 08:57:31 GMT",
            "source_nm": "truth",
            "source_url": "https://adevarul.ro",
            "desc": "Era seara de Mo\u015f Nicolae \u015fi locatarii din blocul de l\u00e2ng\u0103 Terasa Fericirii abia reu\u015fiser\u0103 s\u0103-\u015fi culce copiii, dup\u0103 ce b\u0103gaser\u0103 desigur re\u015fourile \u00een priz\u0103, pentru c\u0103 ..."
        },
        {
            "title": "The Road to Clients&#39; Skepticism at 1 billion Emails per Year in 15 Years of White Image - Business24.ro",
            "link": "http://www.business24.ro/internet/servicii-web/drumul-de-la-scepticismul-clientilor-la-1-miliard-de-email-uri-pe-an-in-15-ani-de-white-image-infografic-1599835",
            "pub_date": "2018-12-06 13:25:00 GMT",
            "source_nm": "Business24.ro",
            "source_url": "http://www.business24.ro",
            "desc": "White Image, prima agentie de email marketing din Romania, aniverseaza 15 ani de activitate, perioada in care a trecut de la statutul de pionier al pietei locale, ..."
        },
        {
            "title": "Large-scale search in Bucharest and 5 counties, in a file of credit deception - Realitatea",
            "link": "https://m.realitatea.net/perchezi-ii-de-amploare-in-bucure-ti-i-5-jude-e-intr-un-dosar-de-in-elaciune-cu-credite_2172771.html",
            "pub_date": "2018-12-05 06:45:17 GMT",
            "source_nm": "The reality",
            "source_url": "https://m.realitatea.net",
            "desc": "comentarii, Perchezi\u021bii de amploare \u00een Bucure\u0219ti \u0219i 5 jude\u021be, \u00eentr-un dosar de \u00een\u0219el\u0103ciune cu credite, anun\u021b\u0103 Poli\u021bia Capitalei., stiri, realitatea.net."
        },
        {
            "title": "Bucharest&#39;s maternity hospitals could be closed one month a year for hygiene - B365.ro",
            "link": "http://www.b365.ro/maternitatile-din-bucuresti-ar-putea-fi-inchise-cate-o-luna-pe-an-pentru-igienizare_259973.html",
            "pub_date": "2018-12-05 14:35:00 GMT",
            "source_nm": "B365.ro",
            "source_url": "http://www.b365.ro",
            "desc": "\"Av\u00e2nd \u00een vedere cazurile recente de infectare cu stafilococ auriu \u00een cadrul unor maternit\u0103\u021bii din municipiul Bucure\u0219ti,\u00een data de 04 decembrie 2018, la sediul ..."
        },
        {
            "title": "Antonio Casalinho, a ballet dancer, a charity show at ONB for a girl with a rare disease - SuperBEBE.com",
            "link": "https://superbebe.ro/stiri/tinarul-balerin-antonio-casalinho-spectacol-caritabil-la-onb-pentru-o-fetita-cu-o-boala-rara/",
            "pub_date": "2018-12-07 03:03:50 GMT",
            "source_nm": "SuperBEBE.ro",
            "source_url": "https://superbebe.ro",
            "desc": "Tanarul portughez Antonio Casalinho, prezentat in calitate de noua stea a baletului mondial, va dansa pe scena Operei Nationale din Bucuresti (ONB) pe 17 ..."
        },
        {
            "title": "EY Study: 60% of taxpayers consider that an ANAF control will impose additional payment amounts - Business24.ro",
            "link": "http://www.business24.ro/taxe-si-impozite/impozit-microintreprinderi/studiu-ey-60-la-suta-dintre-contribuabili-considera-ca-un-control-anaf-le-va-impune-sume-suplimentare-de-plata-1599857",
            "pub_date": "2018-12-07 09:43:00 GMT",
            "source_nm": "Business24.ro",
            "source_url": "http://www.business24.ro",
            "desc": "Desi toti directorii financiari inclusi in sondajul efectuat de EY Romania considera ca au aplicat corect legea fiscala, aproape 60% dintre ei sunt de parere ca ..."
        },
        {
            "title": "Bucharest Parliamentary, Conclusions at the Centenary: &quot;Romania Should Set As a Country of Unirea Project&quot; - Open.md - News portal",
            "link": "https://deschide.md/ro/stiri/politic/40856/Parlamentar-de-la-Bucure%C8%99ti-concluzii-la-Centenar-%E2%80%9ERom%C3%A2nia-trebuie-s%C4%83-%C3%AE%C8%99i-stabileasc%C4%83-ca-proiect-de-%C8%9Bar%C4%83-Unirea%E2%80%9D.htm",
            "pub_date": "2018-12-06 16:10:47 GMT",
            "source_nm": "Open .MD - news portal",
            "source_url": "https://deschide.md",
            "desc": "Deputatul Daniel Gheorghe a sus\u021binut miercuri, de la tribuna Parlamentului de la Bucure\u0219ti, o declara\u021bie politic\u0103 sub genericul \u201eConcluzii la Centenarul Marii ..."
        },
        {
            "title": "Account Executive @ Minio Studio - IQads",
            "link": "https://www.iqads.ro/adjob/18134/account-executive-minio-studio",
            "pub_date": "2018-12-07 07:52:41 GMT",
            "source_nm": "IQads",
            "source_url": "https://www.iqads.ro",
            "desc": "Avem doar 2 ani \u0219i suntem deja pe locul 33 \u00een Topul Forbes al agen\u021biilor de publicitate. Ne m\u00e2ndrim cu trei premii la Romanian PR Awards, inclusiv un Gold, ..."
        }
    ]
}