{
    "src_link": "https://news.google.com/topics/CAAqIggKIhxDQkFTRHdvSkwyMHZNRE5qTVRRd0VnSnNkQ2dBUAE?hl=lt&gl=LT&ceid=LT:lt",
    "language": "lt",
    "get_time": "2018-12-08 12:02:50 GMT",
    "content": [
        {
            "title": "Former Labor Party Procurator proposes to the Supreme Court - DELFI",
            "link": "https://www.delfi.lt/news/daily/lithuania/buvusia-darbo-partijos-bylos-teiseja-siulo-i-auksciausiaji-teisma.d?id=79802675",
            "pub_date": "2018-12-07 07:43:21 GMT",
            "source_nm": "DELFI",
            "source_url": "https://www.delfi.lt",
            "desc": "DELFI - Buvusi\u0105 Darbo partijos \u201ejuodosios buhalterijos\u201c bylos teis\u0117j\u0105 Daiv\u0105 Pranyt\u0119-Zalieckien\u0119 prezident\u0117 Dalia Grybauskait\u0117 nori skirti Lietuvos Auk\u0161\u010diausiojo ..."
        },
        {
            "title": "The Labor Party will reimburse 220,000 Eur of lost grants - Business Knowledge",
            "link": "https://www.vz.lt/2018/12/04/is-prarastu-dotaciju-darbo-partija-atgaus-220000-eur",
            "pub_date": "2018-12-04 16:56:21 GMT",
            "source_nm": "Business News",
            "source_url": "https://www.vz.lt",
            "desc": "Darbo partija atgaus 220.000 Eur i\u0161 1,8 mln. Eur, kuriuos teismas po \u201ejuodosios buhalterijos\u201c bylos perved\u0117 \u012f biud\u017eet\u0105."
        },
        {
            "title": "Labor Party approved 40 candidates for mayor: election slogan - &quot;I&#39;m responsible for my words&quot; - DELFI",
            "link": "https://www.delfi.lt/news/daily/lithuania/darbo-partija-patvirtino-40-kandidatu-i-merus-rinkiminis-sukis-atsakau-uz-savo-zodzius.d?id=79788035",
            "pub_date": "2018-12-05 19:09:44 GMT",
            "source_nm": "DELFI",
            "source_url": "https://www.delfi.lt",
            "desc": ""
        }
    ]
}